Metadata-Version: 2.1
Name: airflow-livy-operators-sexy
Version: 0.3.2
Summary: Lets Airflow DAGs run Spark jobs via Livy: sessions and/or batches. Forked from panovvv/airflow-livy-operators and changed python to 3.5
Home-page: https://github.com/ssheremeta/airflow-livy-operators
Author: Sergei Sheremeta
Author-email: s.w.sheremeta@gmail.com
License: MIT License
Platform: UNKNOWN
Requires-Python: >=3.5
